<?xml version="1.0" encoding="utf-8"?><DEFECTS><DEFECT>
    <SFA>
      <FILEPATH>D:\AIE\vss Example\Assessments\Assesment Tasks C++\Assesment Task 4 C++\Asteroids\Asteroids\</FILEPATH>
      <FILENAME>Asteroid.cpp</FILENAME>
      <LINE>11</LINE>
      <COLUMN>10</COLUMN>
    </SFA>
    <DEFECTCODE>26495</DEFECTCODE>
    <DESCRIPTION>Variable 'Asteroid::mAsteroidRadius' is uninitialized. Always initialize a member variable (type.6).</DESCRIPTION>
    <FUNCTION>Asteroid::{ctor}</FUNCTION>
    <DECORATED>??0Asteroid@@QEAA@XZ</DECORATED>
    <FUNCLINE>11</FUNCLINE>
    <ADDITIONALINFO>
      <targetSymbol>Asteroid::mAsteroidRadius</targetSymbol>
    </ADDITIONALINFO>
    <PATH></PATH>
  </DEFECT><DEFECT>
    <SFA>
      <FILEPATH>D:\AIE\vss Example\Assessments\Assesment Tasks C++\Assesment Task 4 C++\Asteroids\Asteroids\</FILEPATH>
      <FILENAME>Bullet.cpp</FILENAME>
      <LINE>11</LINE>
      <COLUMN>8</COLUMN>
    </SFA>
    <DEFECTCODE>26495</DEFECTCODE>
    <DESCRIPTION>Variable 'Bullet::mBulletHeight' is uninitialized. Always initialize a member variable (type.6).</DESCRIPTION>
    <FUNCTION>Bullet::{ctor}</FUNCTION>
    <DECORATED>??0Bullet@@QEAA@XZ</DECORATED>
    <FUNCLINE>11</FUNCLINE>
    <ADDITIONALINFO>
      <targetSymbol>Bullet::mBulletHeight</targetSymbol>
    </ADDITIONALINFO>
    <PATH></PATH>
  </DEFECT><DEFECT>
    <SFA>
      <FILEPATH>D:\AIE\vss Example\Assessments\Assesment Tasks C++\Assesment Task 4 C++\Asteroids\Asteroids\</FILEPATH>
      <FILENAME>Game.cpp</FILENAME>
      <LINE>24</LINE>
      <COLUMN>6</COLUMN>
    </SFA>
    <DEFECTCODE>26495</DEFECTCODE>
    <DESCRIPTION>Variable 'Game::entityMax' is uninitialized. Always initialize a member variable (type.6).</DESCRIPTION>
    <FUNCTION>Game::{ctor}</FUNCTION>
    <DECORATED>??0Game@@QEAA@XZ</DECORATED>
    <FUNCLINE>24</FUNCLINE>
    <ADDITIONALINFO>
      <targetSymbol>Game::entityMax</targetSymbol>
    </ADDITIONALINFO>
    <PATH></PATH>
  </DEFECT><DEFECT>
    <SFA>
      <FILEPATH>D:\AIE\vss Example\Assessments\Assesment Tasks C++\Assesment Task 4 C++\Asteroids\Asteroids\</FILEPATH>
      <FILENAME>Game.cpp</FILENAME>
      <LINE>29</LINE>
      <COLUMN>6</COLUMN>
    </SFA>
    <DEFECTCODE>26495</DEFECTCODE>
    <DESCRIPTION>Variable 'Game::entityMax' is uninitialized. Always initialize a member variable (type.6).</DESCRIPTION>
    <FUNCTION>Game::{ctor}</FUNCTION>
    <DECORATED>??0Game@@QEAA@HHV?$basic_string@DU?$char_traits@D@std@@V?$allocator@D@2@@std@@@Z</DECORATED>
    <FUNCLINE>29</FUNCLINE>
    <ADDITIONALINFO>
      <targetSymbol>Game::entityMax</targetSymbol>
    </ADDITIONALINFO>
    <PATH></PATH>
  </DEFECT><DEFECT>
    <SFA>
      <FILEPATH>D:\AIE\vss Example\Assessments\Assesment Tasks C++\Assesment Task 4 C++\Asteroids\Asteroids\</FILEPATH>
      <FILENAME>Ship.cpp</FILENAME>
      <LINE>11</LINE>
      <COLUMN>6</COLUMN>
    </SFA>
    <DEFECTCODE>26495</DEFECTCODE>
    <DESCRIPTION>Variable 'Ship::shipRect' is uninitialized. Always initialize a member variable (type.6).</DESCRIPTION>
    <FUNCTION>Ship::{ctor}</FUNCTION>
    <DECORATED>??0Ship@@QEAA@XZ</DECORATED>
    <FUNCLINE>11</FUNCLINE>
    <ADDITIONALINFO>
      <targetSymbol>Ship::shipRect</targetSymbol>
    </ADDITIONALINFO>
    <PATH></PATH>
  </DEFECT><DEFECT>
    <SFA>
      <FILEPATH>D:\AIE\vss Example\Assessments\Assesment Tasks C++\Assesment Task 4 C++\Asteroids\Asteroids\</FILEPATH>
      <FILENAME>Timer.cpp</FILENAME>
      <LINE>12</LINE>
      <COLUMN>7</COLUMN>
    </SFA>
    <DEFECTCODE>26495</DEFECTCODE>
    <DESCRIPTION>Variable 'Timer::lifetime' is uninitialized. Always initialize a member variable (type.6).</DESCRIPTION>
    <FUNCTION>Timer::{ctor}</FUNCTION>
    <DECORATED>??0Timer@@QEAA@XZ</DECORATED>
    <FUNCLINE>12</FUNCLINE>
    <ADDITIONALINFO>
      <targetSymbol>Timer::lifetime</targetSymbol>
    </ADDITIONALINFO>
    <PATH></PATH>
  </DEFECT><DEFECT>
    <SFA>
      <FILEPATH>D:\AIE\vss Example\Assessments\Assesment Tasks C++\Assesment Task 4 C++\Asteroids\Asteroids\</FILEPATH>
      <FILENAME>Timer.cpp</FILENAME>
      <LINE>17</LINE>
      <COLUMN>7</COLUMN>
    </SFA>
    <DEFECTCODE>26495</DEFECTCODE>
    <DESCRIPTION>Variable 'Timer::lifetime' is uninitialized. Always initialize a member variable (type.6).</DESCRIPTION>
    <FUNCTION>Timer::{ctor}</FUNCTION>
    <DECORATED>??0Timer@@QEAA@M@Z</DECORATED>
    <FUNCLINE>17</FUNCLINE>
    <ADDITIONALINFO>
      <targetSymbol>Timer::lifetime</targetSymbol>
    </ADDITIONALINFO>
    <PATH></PATH>
  </DEFECT></DEFECTS>